{
    "Header": {
        "Engine": {
            "Name": "Brood War",
            "ID": 1,
            "ShortName": "BW"
        },
        "Version": "1.21+",
        "Frames": 1486,
        "StartTime": "2023-09-28T16:23:54-05:00",
        "Title": "2v2 alpha males only FS",
        "MapWidth": 128,
        "MapHeight": 128,
        "AvailSlotsCount": 4,
        "Speed": {
            "Name": "Fastest",
            "ID": 6
        },
        "Type": {
            "Name": "Top vs Bottom",
            "ID": 15,
            "ShortName": "TvB"
        },
        "SubType": 2,
        "Host": "ProGamerMatt",
        "Map": "\u0007\ud22c\ud63c \u00051.3",
        "Players": [
            {
                "SlotID": 3,
                "ID": 0,
                "Type": {
                    "Name": "Human",
                    "ID": 2
                },
                "Race": {
                    "Name": "Terran",
                    "ID": 1,
                    "ShortName": "ran",
                    "Letter": 84
                },
                "Team": 1,
                "Name": "ProGamerMatt",
                "Color": {
                    "Name": "Green",
                    "ID": 8,
                    "RGB": 557064
                },
                "Observer": false
            },
            {
                "SlotID": 1,
                "ID": 255,
                "Type": {
                    "Name": "Computer",
                    "ID": 1
                },
                "Race": {
                    "Name": "Zerg",
                    "ID": 0,
                    "ShortName": "zerg",
                    "Letter": 90
                },
                "Team": 2,
                "Name": "Grendel Brood",
                "Color": {
                    "Name": "Purple",
                    "ID": 3,
                    "RGB": 8929436
                },
                "Observer": false
            }
        ]
    },
    "Commands": {
        "Cmds": [
            {
                "Frame": 18,
                "PlayerID": 0,
                "Type": {
                    "Name": "Select",
                    "ID": 99
                },
                "UnitTags": [
                    11467,
                    11468,
                    11469,
                    11470
                ]
            },
            {
                "Frame": 19,
                "PlayerID": 0,
                "Type": {
                    "Name": "Right Click",
                    "ID": 96
                },
                "Pos": {
                    "X": 3992,
                    "Y": 3812
                },
                "UnitTag": 11484,
                "Unit": {
                    "Name": "None",
                    "ID": 228
                },
                "Queued": false
            },
            {
                "Frame": 35,
                "PlayerID": 0,
                "Type": {
                    "Name": "Select",
                    "ID": 99
                },
                "UnitTags": [
                    11471
                ]
            },
            {
                "Frame": 41,
                "PlayerID": 0,
                "Type": {
                    "Name": "Select",
                    "ID": 99
                },
                "IneffKind": 4,
                "UnitTags": [
                    11467
                ]
            },
            {
                "Frame": 45,
                "PlayerID": 0,
                "Type": {
                    "Name": "Right Click",
                    "ID": 96
                },
                "Pos": {
                    "X": 3987,
                    "Y": 3878
                },
                "UnitTag": 11514,
                "Unit": {
                    "Name": "None",
                    "ID": 228
                },
                "Queued": false
            },
            {
                "Frame": 57,
                "PlayerID": 0,
                "Type": {
                    "Name": "Select",
                    "ID": 99
                },
                "UnitTags": [
                    11470
                ]
            },
            {
                "Frame": 60,
                "PlayerID": 0,
                "Type": {
                    "Name": "Right Click",
                    "ID": 96
                },
                "Pos": {
                    "X": 3994,
                    "Y": 3793
                },
                "UnitTag": 11484,
                "Unit": {
                    "Name": "None",
                    "ID": 228
                },
                "Queued": false
            },
            {
                "Frame": 69,
                "PlayerID": 0,
                "Type": {
                    "Name": "Right Click",
                    "ID": 96
                },
                "Pos": {
                    "X": 4012,
                    "Y": 3776
                },
                "UnitTag": 11480,
                "Unit": {
                    "Name": "None",
                    "ID": 228
                },
                "Queued": false
            },
            {
                "Frame": 77,
                "PlayerID": 0,
                "Type": {
                    "Name": "Select",
                    "ID": 99
                },
                "UnitTags": [
                    11471
                ]
            },
            {
                "Frame": 89,
                "PlayerID": 0,
                "Type": {
                    "Name": "Targeted Order",
                    "ID": 97
                },
                "Pos": {
                    "X": 3829,
                    "Y": 3780
                },
                "UnitTag": 11471,
                "Unit": {
                    "Name": "None",
                    "ID": 228
                },
                "Order": {
                    "Name": "RallyPointUnit",
                    "ID": 39
                },
                "Queued": false
            },
            {
                "Frame": 114,
                "PlayerID": 0,
                "Type": {
                    "Name": "Targeted Order",
                    "ID": 97
                },
                "Pos": {
                    "X": 3829,
                    "Y": 3784
                },
                "UnitTag": 11471,
                "Unit": {
                    "Name": "None",
                    "ID": 228
                },
                "Order": {
                    "Name": "RallyPointUnit",
                    "ID": 39
                },
                "Queued": false
            },
            {
                "Frame": 123,
                "PlayerID": 0,
                "Type": {
                    "Name": "Targeted Order",
                    "ID": 97
                },
                "IneffKind": 3,
                "Pos": {
                    "X": 3829,
                    "Y": 3784
                },
                "UnitTag": 11471,
                "Unit": {
                    "Name": "None",
                    "ID": 228
                },
                "Order": {
                    "Name": "RallyPointUnit",
                    "ID": 39
                },
                "Queued": false
            },
            {
                "Frame": 128,
                "PlayerID": 0,
                "Type": {
                    "Name": "Targeted Order",
                    "ID": 97
                },
                "IneffKind": 3,
                "Pos": {
                    "X": 3828,
                    "Y": 3784
                },
                "UnitTag": 11471,
                "Unit": {
                    "Name": "None",
                    "ID": 228
                },
                "Order": {
                    "Name": "RallyPointUnit",
                    "ID": 39
                },
                "Queued": false
            },
            {
                "Frame": 133,
                "PlayerID": 0,
                "Type": {
                    "Name": "Targeted Order",
                    "ID": 97
                },
                "IneffKind": 3,
                "Pos": {
                    "X": 3828,
                    "Y": 3784
                },
                "UnitTag": 11471,
                "Unit": {
                    "Name": "None",
                    "ID": 228
                },
                "Order": {
                    "Name": "RallyPointUnit",
                    "ID": 39
                },
                "Queued": false
            },
            {
                "Frame": 247,
                "PlayerID": 0,
                "Type": {
                    "Name": "Train",
                    "ID": 31
                },
                "Unit": {
                    "Name": "SCV",
                    "ID": 7
                }
            },
            {
                "Frame": 417,
                "PlayerID": 0,
                "Type": {
                    "Name": "Train",
                    "ID": 31
                },
                "Unit": {
                    "Name": "SCV",
                    "ID": 7
                }
            },
            {
                "Frame": 560,
                "PlayerID": 0,
                "Type": {
                    "Name": "Select",
                    "ID": 99
                },
                "UnitTags": [
                    11457
                ]
            },
            {
                "Frame": 564,
                "PlayerID": 0,
                "Type": {
                    "Name": "Right Click",
                    "ID": 96
                },
                "Pos": {
                    "X": 4020,
                    "Y": 3716
                },
                "UnitTag": 11481,
                "Unit": {
                    "Name": "None",
                    "ID": 228
                },
                "Queued": false
            },
            {
                "Frame": 570,
                "PlayerID": 0,
                "Type": {
                    "Name": "Right Click",
                    "ID": 96
                },
                "Pos": {
                    "X": 4000,
                    "Y": 3684
                },
                "UnitTag": 11483,
                "Unit": {
                    "Name": "None",
                    "ID": 228
                },
                "Queued": false
            },
            {
                "Frame": 589,
                "PlayerID": 0,
                "Type": {
                    "Name": "Select",
                    "ID": 99
                },
                "UnitTags": [
                    11471
                ]
            },
            {
                "Frame": 720,
                "PlayerID": 0,
                "Type": {
                    "Name": "Train",
                    "ID": 31
                },
                "Unit": {
                    "Name": "SCV",
                    "ID": 7
                }
            },
            {
                "Frame": 860,
                "PlayerID": 0,
                "Type": {
                    "Name": "Select",
                    "ID": 99
                },
                "UnitTags": [
                    11455
                ]
            },
            {
                "Frame": 861,
                "PlayerID": 0,
                "Type": {
                    "Name": "Right Click",
                    "ID": 96
                },
                "Pos": {
                    "X": 3968,
                    "Y": 3770
                },
                "UnitTag": 11482,
                "Unit": {
                    "Name": "None",
                    "ID": 228
                },
                "Queued": false
            },
            {
                "Frame": 877,
                "PlayerID": 0,
                "Type": {
                    "Name": "Select",
                    "ID": 99
                },
                "UnitTags": [
                    11471
                ]
            },
            {
                "Frame": 1164,
                "PlayerID": 0,
                "Type": {
                    "Name": "Select",
                    "ID": 99
                },
                "UnitTags": [
                    11453
                ]
            },
            {
                "Frame": 1166,
                "PlayerID": 0,
                "Type": {
                    "Name": "Right Click",
                    "ID": 96
                },
                "Pos": {
                    "X": 3952,
                    "Y": 3945
                },
                "UnitTag": 11485,
                "Unit": {
                    "Name": "None",
                    "ID": 228
                },
                "Queued": false
            },
            {
                "Frame": 1178,
                "PlayerID": 0,
                "Type": {
                    "Name": "Select",
                    "ID": 99
                },
                "UnitTags": [
                    11471
                ]
            },
            {
                "Frame": 1201,
                "PlayerID": 0,
                "Type": {
                    "Name": "Train",
                    "ID": 31
                },
                "Unit": {
                    "Name": "SCV",
                    "ID": 7
                }
            },
            {
                "Frame": 1205,
                "PlayerID": 0,
                "Type": {
                    "Name": "Train",
                    "ID": 31
                },
                "Unit": {
                    "Name": "SCV",
                    "ID": 7
                }
            },
            {
                "Frame": 1208,
                "PlayerID": 0,
                "Type": {
                    "Name": "Train",
                    "ID": 31
                },
                "Unit": {
                    "Name": "SCV",
                    "ID": 7
                }
            },
            {
                "Frame": 1210,
                "PlayerID": 0,
                "Type": {
                    "Name": "Train",
                    "ID": 31
                },
                "Unit": {
                    "Name": "SCV",
                    "ID": 7
                }
            },
            {
                "Frame": 1215,
                "PlayerID": 0,
                "Type": {
                    "Name": "Train",
                    "ID": 31
                },
                "Unit": {
                    "Name": "SCV",
                    "ID": 7
                }
            },
            {
                "Frame": 1218,
                "PlayerID": 0,
                "Type": {
                    "Name": "Train",
                    "ID": 31
                },
                "IneffKind": 1,
                "Unit": {
                    "Name": "SCV",
                    "ID": 7
                }
            },
            {
                "Frame": 1224,
                "PlayerID": 0,
                "Type": {
                    "Name": "Train",
                    "ID": 31
                },
                "IneffKind": 1,
                "Unit": {
                    "Name": "SCV",
                    "ID": 7
                }
            },
            {
                "Frame": 1227,
                "PlayerID": 0,
                "Type": {
                    "Name": "Train",
                    "ID": 31
                },
                "IneffKind": 1,
                "Unit": {
                    "Name": "SCV",
                    "ID": 7
                }
            },
            {
                "Frame": 1230,
                "PlayerID": 0,
                "Type": {
                    "Name": "Train",
                    "ID": 31
                },
                "IneffKind": 1,
                "Unit": {
                    "Name": "SCV",
                    "ID": 7
                }
            },
            {
                "Frame": 1234,
                "PlayerID": 0,
                "Type": {
                    "Name": "Train",
                    "ID": 31
                },
                "IneffKind": 1,
                "Unit": {
                    "Name": "SCV",
                    "ID": 7
                }
            },
            {
                "Frame": 1241,
                "PlayerID": 0,
                "Type": {
                    "Name": "Train",
                    "ID": 31
                },
                "IneffKind": 1,
                "Unit": {
                    "Name": "SCV",
                    "ID": 7
                }
            },
            {
                "Frame": 1242,
                "PlayerID": 0,
                "Type": {
                    "Name": "Train",
                    "ID": 31
                },
                "IneffKind": 1,
                "Unit": {
                    "Name": "SCV",
                    "ID": 7
                }
            },
            {
                "Frame": 1244,
                "PlayerID": 0,
                "Type": {
                    "Name": "Train",
                    "ID": 31
                },
                "IneffKind": 1,
                "Unit": {
                    "Name": "SCV",
                    "ID": 7
                }
            },
            {
                "Frame": 1249,
                "PlayerID": 0,
                "Type": {
                    "Name": "Train",
                    "ID": 31
                },
                "IneffKind": 1,
                "Unit": {
                    "Name": "SCV",
                    "ID": 7
                }
            },
            {
                "Frame": 1252,
                "PlayerID": 0,
                "Type": {
                    "Name": "Train",
                    "ID": 31
                },
                "IneffKind": 1,
                "Unit": {
                    "Name": "SCV",
                    "ID": 7
                }
            },
            {
                "Frame": 1254,
                "PlayerID": 0,
                "Type": {
                    "Name": "Train",
                    "ID": 31
                },
                "IneffKind": 1,
                "Unit": {
                    "Name": "SCV",
                    "ID": 7
                }
            },
            {
                "Frame": 1259,
                "PlayerID": 0,
                "Type": {
                    "Name": "Train",
                    "ID": 31
                },
                "IneffKind": 1,
                "Unit": {
                    "Name": "SCV",
                    "ID": 7
                }
            },
            {
                "Frame": 1263,
                "PlayerID": 0,
                "Type": {
                    "Name": "Train",
                    "ID": 31
                },
                "IneffKind": 1,
                "Unit": {
                    "Name": "SCV",
                    "ID": 7
                }
            },
            {
                "Frame": 1268,
                "PlayerID": 0,
                "Type": {
                    "Name": "Train",
                    "ID": 31
                },
                "IneffKind": 1,
                "Unit": {
                    "Name": "SCV",
                    "ID": 7
                }
            },
            {
                "Frame": 1271,
                "PlayerID": 0,
                "Type": {
                    "Name": "Train",
                    "ID": 31
                },
                "IneffKind": 1,
                "Unit": {
                    "Name": "SCV",
                    "ID": 7
                }
            },
            {
                "Frame": 1275,
                "PlayerID": 0,
                "Type": {
                    "Name": "Train",
                    "ID": 31
                },
                "IneffKind": 1,
                "Unit": {
                    "Name": "SCV",
                    "ID": 7
                }
            },
            {
                "Frame": 1278,
                "PlayerID": 0,
                "Type": {
                    "Name": "Train",
                    "ID": 31
                },
                "IneffKind": 1,
                "Unit": {
                    "Name": "SCV",
                    "ID": 7
                }
            },
            {
                "Frame": 1283,
                "PlayerID": 0,
                "Type": {
                    "Name": "Train",
                    "ID": 31
                },
                "IneffKind": 1,
                "Unit": {
                    "Name": "SCV",
                    "ID": 7
                }
            },
            {
                "Frame": 1286,
                "PlayerID": 0,
                "Type": {
                    "Name": "Train",
                    "ID": 31
                },
                "IneffKind": 1,
                "Unit": {
                    "Name": "SCV",
                    "ID": 7
                }
            },
            {
                "Frame": 1288,
                "PlayerID": 0,
                "Type": {
                    "Name": "Train",
                    "ID": 31
                },
                "IneffKind": 1,
                "Unit": {
                    "Name": "SCV",
                    "ID": 7
                }
            },
            {
                "Frame": 1293,
                "PlayerID": 0,
                "Type": {
                    "Name": "Train",
                    "ID": 31
                },
                "IneffKind": 1,
                "Unit": {
                    "Name": "SCV",
                    "ID": 7
                }
            },
            {
                "Frame": 1297,
                "PlayerID": 0,
                "Type": {
                    "Name": "Train",
                    "ID": 31
                },
                "IneffKind": 1,
                "Unit": {
                    "Name": "SCV",
                    "ID": 7
                }
            },
            {
                "Frame": 1300,
                "PlayerID": 0,
                "Type": {
                    "Name": "Train",
                    "ID": 31
                },
                "IneffKind": 1,
                "Unit": {
                    "Name": "SCV",
                    "ID": 7
                }
            },
            {
                "Frame": 1303,
                "PlayerID": 0,
                "Type": {
                    "Name": "Train",
                    "ID": 31
                },
                "IneffKind": 1,
                "Unit": {
                    "Name": "SCV",
                    "ID": 7
                }
            },
            {
                "Frame": 1307,
                "PlayerID": 0,
                "Type": {
                    "Name": "Train",
                    "ID": 31
                },
                "IneffKind": 1,
                "Unit": {
                    "Name": "SCV",
                    "ID": 7
                }
            },
            {
                "Frame": 1312,
                "PlayerID": 0,
                "Type": {
                    "Name": "Train",
                    "ID": 31
                },
                "IneffKind": 1,
                "Unit": {
                    "Name": "SCV",
                    "ID": 7
                }
            },
            {
                "Frame": 1315,
                "PlayerID": 0,
                "Type": {
                    "Name": "Train",
                    "ID": 31
                },
                "IneffKind": 1,
                "Unit": {
                    "Name": "SCV",
                    "ID": 7
                }
            },
            {
                "Frame": 1319,
                "PlayerID": 0,
                "Type": {
                    "Name": "Train",
                    "ID": 31
                },
                "IneffKind": 1,
                "Unit": {
                    "Name": "SCV",
                    "ID": 7
                }
            },
            {
                "Frame": 1322,
                "PlayerID": 0,
                "Type": {
                    "Name": "Train",
                    "ID": 31
                },
                "IneffKind": 1,
                "Unit": {
                    "Name": "SCV",
                    "ID": 7
                }
            },
            {
                "Frame": 1326,
                "PlayerID": 0,
                "Type": {
                    "Name": "Train",
                    "ID": 31
                },
                "IneffKind": 1,
                "Unit": {
                    "Name": "SCV",
                    "ID": 7
                }
            },
            {
                "Frame": 1329,
                "PlayerID": 0,
                "Type": {
                    "Name": "Train",
                    "ID": 31
                },
                "IneffKind": 1,
                "Unit": {
                    "Name": "SCV",
                    "ID": 7
                }
            },
            {
                "Frame": 1332,
                "PlayerID": 0,
                "Type": {
                    "Name": "Train",
                    "ID": 31
                },
                "IneffKind": 1,
                "Unit": {
                    "Name": "SCV",
                    "ID": 7
                }
            },
            {
                "Frame": 1337,
                "PlayerID": 0,
                "Type": {
                    "Name": "Train",
                    "ID": 31
                },
                "IneffKind": 1,
                "Unit": {
                    "Name": "SCV",
                    "ID": 7
                }
            },
            {
                "Frame": 1341,
                "PlayerID": 0,
                "Type": {
                    "Name": "Train",
                    "ID": 31
                },
                "IneffKind": 1,
                "Unit": {
                    "Name": "SCV",
                    "ID": 7
                }
            },
            {
                "Frame": 1344,
                "PlayerID": 0,
                "Type": {
                    "Name": "Train",
                    "ID": 31
                },
                "IneffKind": 1,
                "Unit": {
                    "Name": "SCV",
                    "ID": 7
                }
            },
            {
                "Frame": 1349,
                "PlayerID": 0,
                "Type": {
                    "Name": "Train",
                    "ID": 31
                },
                "IneffKind": 1,
                "Unit": {
                    "Name": "SCV",
                    "ID": 7
                }
            },
            {
                "Frame": 1351,
                "PlayerID": 0,
                "Type": {
                    "Name": "Train",
                    "ID": 31
                },
                "IneffKind": 1,
                "Unit": {
                    "Name": "SCV",
                    "ID": 7
                }
            },
            {
                "Frame": 1356,
                "PlayerID": 0,
                "Type": {
                    "Name": "Train",
                    "ID": 31
                },
                "IneffKind": 1,
                "Unit": {
                    "Name": "SCV",
                    "ID": 7
                }
            },
            {
                "Frame": 1360,
                "PlayerID": 0,
                "Type": {
                    "Name": "Train",
                    "ID": 31
                },
                "IneffKind": 1,
                "Unit": {
                    "Name": "SCV",
                    "ID": 7
                }
            },
            {
                "Frame": 1365,
                "PlayerID": 0,
                "Type": {
                    "Name": "Train",
                    "ID": 31
                },
                "IneffKind": 1,
                "Unit": {
                    "Name": "SCV",
                    "ID": 7
                }
            },
            {
                "Frame": 1368,
                "PlayerID": 0,
                "Type": {
                    "Name": "Train",
                    "ID": 31
                },
                "IneffKind": 1,
                "Unit": {
                    "Name": "SCV",
                    "ID": 7
                }
            },
            {
                "Frame": 1372,
                "PlayerID": 0,
                "Type": {
                    "Name": "Train",
                    "ID": 31
                },
                "IneffKind": 1,
                "Unit": {
                    "Name": "SCV",
                    "ID": 7
                }
            },
            {
                "Frame": 1377,
                "PlayerID": 0,
                "Type": {
                    "Name": "Train",
                    "ID": 31
                },
                "IneffKind": 1,
                "Unit": {
                    "Name": "SCV",
                    "ID": 7
                }
            },
            {
                "Frame": 1380,
                "PlayerID": 0,
                "Type": {
                    "Name": "Train",
                    "ID": 31
                },
                "IneffKind": 1,
                "Unit": {
                    "Name": "SCV",
                    "ID": 7
                }
            },
            {
                "Frame": 1385,
                "PlayerID": 0,
                "Type": {
                    "Name": "Train",
                    "ID": 31
                },
                "IneffKind": 1,
                "Unit": {
                    "Name": "SCV",
                    "ID": 7
                }
            },
            {
                "Frame": 1389,
                "PlayerID": 0,
                "Type": {
                    "Name": "Train",
                    "ID": 31
                },
                "IneffKind": 1,
                "Unit": {
                    "Name": "SCV",
                    "ID": 7
                }
            },
            {
                "Frame": 1392,
                "PlayerID": 0,
                "Type": {
                    "Name": "Train",
                    "ID": 31
                },
                "IneffKind": 1,
                "Unit": {
                    "Name": "SCV",
                    "ID": 7
                }
            },
            {
                "Frame": 1395,
                "PlayerID": 0,
                "Type": {
                    "Name": "Train",
                    "ID": 31
                },
                "IneffKind": 1,
                "Unit": {
                    "Name": "SCV",
                    "ID": 7
                }
            },
            {
                "Frame": 1400,
                "PlayerID": 0,
                "Type": {
                    "Name": "Train",
                    "ID": 31
                },
                "IneffKind": 1,
                "Unit": {
                    "Name": "SCV",
                    "ID": 7
                }
            },
            {
                "Frame": 1404,
                "PlayerID": 0,
                "Type": {
                    "Name": "Train",
                    "ID": 31
                },
                "IneffKind": 1,
                "Unit": {
                    "Name": "SCV",
                    "ID": 7
                }
            },
            {
                "Frame": 1409,
                "PlayerID": 0,
                "Type": {
                    "Name": "Train",
                    "ID": 31
                },
                "IneffKind": 1,
                "Unit": {
                    "Name": "SCV",
                    "ID": 7
                }
            },
            {
                "Frame": 1411,
                "PlayerID": 0,
                "Type": {
                    "Name": "Train",
                    "ID": 31
                },
                "IneffKind": 1,
                "Unit": {
                    "Name": "SCV",
                    "ID": 7
                }
            },
            {
                "Frame": 1417,
                "PlayerID": 0,
                "Type": {
                    "Name": "Train",
                    "ID": 31
                },
                "IneffKind": 1,
                "Unit": {
                    "Name": "SCV",
                    "ID": 7
                }
            },
            {
                "Frame": 1421,
                "PlayerID": 0,
                "Type": {
                    "Name": "Train",
                    "ID": 31
                },
                "IneffKind": 1,
                "Unit": {
                    "Name": "SCV",
                    "ID": 7
                }
            },
            {
                "Frame": 1424,
                "PlayerID": 0,
                "Type": {
                    "Name": "Train",
                    "ID": 31
                },
                "IneffKind": 1,
                "Unit": {
                    "Name": "SCV",
                    "ID": 7
                }
            },
            {
                "Frame": 1429,
                "PlayerID": 0,
                "Type": {
                    "Name": "Train",
                    "ID": 31
                },
                "IneffKind": 1,
                "Unit": {
                    "Name": "SCV",
                    "ID": 7
                }
            },
            {
                "Frame": 1431,
                "PlayerID": 0,
                "Type": {
                    "Name": "Train",
                    "ID": 31
                },
                "IneffKind": 1,
                "Unit": {
                    "Name": "SCV",
                    "ID": 7
                }
            },
            {
                "Frame": 1436,
                "PlayerID": 0,
                "Type": {
                    "Name": "Train",
                    "ID": 31
                },
                "IneffKind": 1,
                "Unit": {
                    "Name": "SCV",
                    "ID": 7
                }
            },
            {
                "Frame": 1440,
                "PlayerID": 0,
                "Type": {
                    "Name": "Train",
                    "ID": 31
                },
                "IneffKind": 1,
                "Unit": {
                    "Name": "SCV",
                    "ID": 7
                }
            }
        ],
        "ParseErrCmds": null
    },
    "MapData": null,
    "Computed": {
        "LeaveGameCmds": null,
        "ChatCmds": null,
        "WinnerTeam": 0,
        "RepSaverPlayerID": null,
        "PlayerDescs": [
            {
                "PlayerID": 0,
                "LastCmdFrame": 1440,
                "CmdCount": 91,
                "APM": 90,
                "EffectiveCmdCount": 28,
                "EAPM": 28,
                "StartLocation": {
                    "X": 3808,
                    "Y": 3792
                },
                "StartDirection": 4
            },
            {
                "PlayerID": 255,
                "LastCmdFrame": 0,
                "CmdCount": 0,
                "APM": 0,
                "EffectiveCmdCount": 0,
                "EAPM": 0,
                "StartLocation": {
                    "X": 288,
                    "Y": 240
                },
                "StartDirection": 11
            }
        ]
    }
}